{
  "nodes": [
    {
      "id": "d_projects_b_fit_v2_docs_improvements_chunk_f_muscle_set_counts_md",
      "label": "chunk-f-muscle-set-counts.md",
      "file_type": "document",
      "source_file": "D:\\Projects\\b-fit v2\\docs\\improvements\\chunk-f-muscle-set-counts.md",
      "source_location": "L1"
    },
    {
      "id": "improvements_chunk_f_muscle_set_counts_chunk_f_muscle_group_set_counts_7",
      "label": "Chunk F \u2014 Muscle-group set counts (#7)",
      "file_type": "document",
      "source_file": "D:\\Projects\\b-fit v2\\docs\\improvements\\chunk-f-muscle-set-counts.md",
      "source_location": "L1"
    },
    {
      "id": "improvements_chunk_f_muscle_set_counts_decision_confirmed_with_user",
      "label": "Decision (confirmed with user)",
      "file_type": "document",
      "source_file": "D:\\Projects\\b-fit v2\\docs\\improvements\\chunk-f-muscle-set-counts.md",
      "source_location": "L12"
    },
    {
      "id": "improvements_chunk_f_muscle_set_counts_shared_building_blocks",
      "label": "Shared building blocks",
      "file_type": "document",
      "source_file": "D:\\Projects\\b-fit v2\\docs\\improvements\\chunk-f-muscle-set-counts.md",
      "source_location": "L20"
    },
    {
      "id": "improvements_chunk_f_muscle_set_counts_helper_src_lib_analytics_muscle_set_counts_ts_new_pure",
      "label": "Helper \u2014 `src/lib/analytics/muscle-set-counts.ts` (new, pure)",
      "file_type": "document",
      "source_file": "D:\\Projects\\b-fit v2\\docs\\improvements\\chunk-f-muscle-set-counts.md",
      "source_location": "L22"
    },
    {
      "id": "improvements_chunk_f_muscle_set_counts_codeblock_1",
      "label": "code:ts (computeMuscleGroupSetCounts(items: MuscleSetCountInput[]): M)",
      "file_type": "document",
      "source_file": "D:\\Projects\\b-fit v2\\docs\\improvements\\chunk-f-muscle-set-counts.md",
      "source_location": "L24"
    },
    {
      "id": "improvements_chunk_f_muscle_set_counts_component_src_components_features_workouts_musclegroupsetcounts_tsx_new",
      "label": "Component \u2014 `src/components/features/workouts/MuscleGroupSetCounts.tsx` (new)",
      "file_type": "document",
      "source_file": "D:\\Projects\\b-fit v2\\docs\\improvements\\chunk-f-muscle-set-counts.md",
      "source_location": "L37"
    },
    {
      "id": "improvements_chunk_f_muscle_set_counts_integration_points_set_source_per_context",
      "label": "Integration points (set source per context)",
      "file_type": "document",
      "source_file": "D:\\Projects\\b-fit v2\\docs\\improvements\\chunk-f-muscle-set-counts.md",
      "source_location": "L44"
    },
    {
      "id": "improvements_chunk_f_muscle_set_counts_files_touched",
      "label": "Files touched",
      "file_type": "document",
      "source_file": "D:\\Projects\\b-fit v2\\docs\\improvements\\chunk-f-muscle-set-counts.md",
      "source_location": "L65"
    },
    {
      "id": "improvements_chunk_f_muscle_set_counts_codeblock_2",
      "label": "code:block2 (src/lib/analytics/muscle-set-counts.ts                      )",
      "file_type": "document",
      "source_file": "D:\\Projects\\b-fit v2\\docs\\improvements\\chunk-f-muscle-set-counts.md",
      "source_location": "L67"
    },
    {
      "id": "improvements_chunk_f_muscle_set_counts_validation",
      "label": "Validation",
      "file_type": "document",
      "source_file": "D:\\Projects\\b-fit v2\\docs\\improvements\\chunk-f-muscle-set-counts.md",
      "source_location": "L83"
    },
    {
      "id": "improvements_chunk_f_muscle_set_counts_carry_overs_considerations",
      "label": "Carry-overs / considerations",
      "file_type": "document",
      "source_file": "D:\\Projects\\b-fit v2\\docs\\improvements\\chunk-f-muscle-set-counts.md",
      "source_location": "L99"
    }
  ],
  "edges": [
    {
      "source": "d_projects_b_fit_v2_docs_improvements_chunk_f_muscle_set_counts_md",
      "target": "improvements_chunk_f_muscle_set_counts_chunk_f_muscle_group_set_counts_7",
      "relation": "contains",
      "confidence": "EXTRACTED",
      "source_file": "D:\\Projects\\b-fit v2\\docs\\improvements\\chunk-f-muscle-set-counts.md",
      "source_location": "L1",
      "weight": 1.0
    },
    {
      "source": "improvements_chunk_f_muscle_set_counts_chunk_f_muscle_group_set_counts_7",
      "target": "improvements_chunk_f_muscle_set_counts_decision_confirmed_with_user",
      "relation": "contains",
      "confidence": "EXTRACTED",
      "source_file": "D:\\Projects\\b-fit v2\\docs\\improvements\\chunk-f-muscle-set-counts.md",
      "source_location": "L12",
      "weight": 1.0
    },
    {
      "source": "improvements_chunk_f_muscle_set_counts_chunk_f_muscle_group_set_counts_7",
      "target": "improvements_chunk_f_muscle_set_counts_shared_building_blocks",
      "relation": "contains",
      "confidence": "EXTRACTED",
      "source_file": "D:\\Projects\\b-fit v2\\docs\\improvements\\chunk-f-muscle-set-counts.md",
      "source_location": "L20",
      "weight": 1.0
    },
    {
      "source": "improvements_chunk_f_muscle_set_counts_shared_building_blocks",
      "target": "improvements_chunk_f_muscle_set_counts_helper_src_lib_analytics_muscle_set_counts_ts_new_pure",
      "relation": "contains",
      "confidence": "EXTRACTED",
      "source_file": "D:\\Projects\\b-fit v2\\docs\\improvements\\chunk-f-muscle-set-counts.md",
      "source_location": "L22",
      "weight": 1.0
    },
    {
      "source": "improvements_chunk_f_muscle_set_counts_helper_src_lib_analytics_muscle_set_counts_ts_new_pure",
      "target": "improvements_chunk_f_muscle_set_counts_codeblock_1",
      "relation": "contains",
      "confidence": "EXTRACTED",
      "source_file": "D:\\Projects\\b-fit v2\\docs\\improvements\\chunk-f-muscle-set-counts.md",
      "source_location": "L24",
      "weight": 1.0
    },
    {
      "source": "improvements_chunk_f_muscle_set_counts_shared_building_blocks",
      "target": "improvements_chunk_f_muscle_set_counts_component_src_components_features_workouts_musclegroupsetcounts_tsx_new",
      "relation": "contains",
      "confidence": "EXTRACTED",
      "source_file": "D:\\Projects\\b-fit v2\\docs\\improvements\\chunk-f-muscle-set-counts.md",
      "source_location": "L37",
      "weight": 1.0
    },
    {
      "source": "improvements_chunk_f_muscle_set_counts_chunk_f_muscle_group_set_counts_7",
      "target": "improvements_chunk_f_muscle_set_counts_integration_points_set_source_per_context",
      "relation": "contains",
      "confidence": "EXTRACTED",
      "source_file": "D:\\Projects\\b-fit v2\\docs\\improvements\\chunk-f-muscle-set-counts.md",
      "source_location": "L44",
      "weight": 1.0
    },
    {
      "source": "improvements_chunk_f_muscle_set_counts_chunk_f_muscle_group_set_counts_7",
      "target": "improvements_chunk_f_muscle_set_counts_files_touched",
      "relation": "contains",
      "confidence": "EXTRACTED",
      "source_file": "D:\\Projects\\b-fit v2\\docs\\improvements\\chunk-f-muscle-set-counts.md",
      "source_location": "L65",
      "weight": 1.0
    },
    {
      "source": "improvements_chunk_f_muscle_set_counts_files_touched",
      "target": "improvements_chunk_f_muscle_set_counts_codeblock_2",
      "relation": "contains",
      "confidence": "EXTRACTED",
      "source_file": "D:\\Projects\\b-fit v2\\docs\\improvements\\chunk-f-muscle-set-counts.md",
      "source_location": "L67",
      "weight": 1.0
    },
    {
      "source": "improvements_chunk_f_muscle_set_counts_chunk_f_muscle_group_set_counts_7",
      "target": "improvements_chunk_f_muscle_set_counts_validation",
      "relation": "contains",
      "confidence": "EXTRACTED",
      "source_file": "D:\\Projects\\b-fit v2\\docs\\improvements\\chunk-f-muscle-set-counts.md",
      "source_location": "L83",
      "weight": 1.0
    },
    {
      "source": "improvements_chunk_f_muscle_set_counts_chunk_f_muscle_group_set_counts_7",
      "target": "improvements_chunk_f_muscle_set_counts_carry_overs_considerations",
      "relation": "contains",
      "confidence": "EXTRACTED",
      "source_file": "D:\\Projects\\b-fit v2\\docs\\improvements\\chunk-f-muscle-set-counts.md",
      "source_location": "L99",
      "weight": 1.0
    }
  ],
  "input_tokens": 0,
  "output_tokens": 0
}
